<annotation>
	<folder>menwithfootwear</folder>
	<filename>11094509_879288222133166_804342908_n.jpg</filename>
	<path>/Users/ok/shoe_scrape/menwithfootwear/11094509_879288222133166_804342908_n.jpg</path>
	<source>
		<database>Unknown</database>
	</source>
	<size>
		<width>640</width>
		<height>640</height>
		<depth>3</depth>
	</size>
	<segmented>0</segmented>
	<object>
		<name>sneaker</name>
		<pose>Unspecified</pose>
		<truncated>0</truncated>
		<difficult>0</difficult>
		<bndbox>
			<xmin>289</xmin>
			<ymin>101</ymin>
			<xmax>570</xmax>
			<ymax>483</ymax>
		</bndbox>
	</object>
	<object>
		<name>sneaker</name>
		<pose>Unspecified</pose>
		<truncated>0</truncated>
		<difficult>0</difficult>
		<bndbox>
			<xmin>145</xmin>
			<ymin>63</ymin>
			<xmax>286</xmax>
			<ymax>271</ymax>
		</bndbox>
	</object>
</annotation>
