<annotation verified="yes">
	<folder>menwithfootwear</folder>
	<filename>11385608_444633872376823_50075274_n.jpg</filename>
	<path>/Users/ok/shoe_scrape/menwithfootwear/11385608_444633872376823_50075274_n.jpg</path>
	<source>
		<database>Unknown</database>
	</source>
	<size>
		<width>640</width>
		<height>640</height>
		<depth>3</depth>
	</size>
	<segmented>0</segmented>
	<object>
		<name>sneaker</name>
		<pose>Unspecified</pose>
		<truncated>1</truncated>
		<difficult>0</difficult>
		<bndbox>
			<xmin>1</xmin>
			<ymin>399</ymin>
			<xmax>155</xmax>
			<ymax>584</ymax>
		</bndbox>
	</object>
	<object>
		<name>sneaker</name>
		<pose>Unspecified</pose>
		<truncated>0</truncated>
		<difficult>0</difficult>
		<bndbox>
			<xmin>151</xmin>
			<ymin>379</ymin>
			<xmax>232</xmax>
			<ymax>527</ymax>
		</bndbox>
	</object>
	<object>
		<name>sneaker</name>
		<pose>Unspecified</pose>
		<truncated>0</truncated>
		<difficult>0</difficult>
		<bndbox>
			<xmin>294</xmin>
			<ymin>478</ymin>
			<xmax>341</xmax>
			<ymax>531</ymax>
		</bndbox>
	</object>
	<object>
		<name>sneaker</name>
		<pose>Unspecified</pose>
		<truncated>1</truncated>
		<difficult>0</difficult>
		<bndbox>
			<xmin>182</xmin>
			<ymin>360</ymin>
			<xmax>329</xmax>
			<ymax>640</ymax>
		</bndbox>
	</object>
	<object>
		<name>sneaker</name>
		<pose>Unspecified</pose>
		<truncated>0</truncated>
		<difficult>0</difficult>
		<bndbox>
			<xmin>333</xmin>
			<ymin>395</ymin>
			<xmax>572</xmax>
			<ymax>639</ymax>
		</bndbox>
	</object>
	<object>
		<name>sneaker</name>
		<pose>Unspecified</pose>
		<truncated>0</truncated>
		<difficult>0</difficult>
		<bndbox>
			<xmin>384</xmin>
			<ymin>373</ymin>
			<xmax>499</xmax>
			<ymax>460</ymax>
		</bndbox>
	</object>
	<object>
		<name>sneaker</name>
		<pose>Unspecified</pose>
		<truncated>1</truncated>
		<difficult>0</difficult>
		<bndbox>
			<xmin>499</xmin>
			<ymin>382</ymin>
			<xmax>640</xmax>
			<ymax>482</ymax>
		</bndbox>
	</object>
</annotation>
